emcdproj/data/.gitignore
emcdproj/data/copier/answers-default.yaml
emcdproj/data/copier/answers-maximum.yaml
emcdproj/data/templates/coverage.svg.jinja
emcdproj/data/templates/website.html.jinja
emcdproj/README.rst
emcdproj/__init__.py
emcdproj/__main__.py
emcdproj/cli.py
emcdproj/exceptions.py
emcdproj/filesystem.py
emcdproj/interfaces.py
emcdproj/py.typed
emcdproj/template.py
emcdproj/website.py
emcdproj/__/__init__.py
emcdproj/__/imports.py
emcdproj/__/nomina.py
emcdproj/_typedecls/__builtins__.pyi
emcd_projects-1.36.dist-info/METADATA
emcd_projects-1.36.dist-info/WHEEL
emcd_projects-1.36.dist-info/entry_points.txt
emcd_projects-1.36.dist-info/licenses/LICENSE.txt
emcd_projects-1.36.dist-info/RECORD
