Metadata-Version: 2.4
Name: emcd-projects
Version: 1.36
Summary: Project management utilities.
Project-URL: Homepage, https://github.com/emcd/python-project-common
Project-URL: Documentation, https://emcd.github.io/python-project-common
Project-URL: Download, https://pypi.org/project/emcd-projects/#files
Project-URL: Source Code, https://github.com/emcd/python-project-common
Project-URL: Issue Tracker, https://github.com/emcd/python-project-common/issues
Author-email: Eric McDonald <emcd@users.noreply.github.com>
License-Expression: Apache-2.0
License-File: LICENSE.txt
Keywords: maintenance,project,template
Classifier: Development Status :: 3 - Alpha
Classifier: Intended Audience :: Developers
Classifier: License :: OSI Approved :: Apache Software License
Classifier: Programming Language :: Python :: 3 :: Only
Classifier: Programming Language :: Python :: 3.10
Classifier: Programming Language :: Python :: 3.11
Classifier: Programming Language :: Python :: 3.12
Classifier: Programming Language :: Python :: 3.13
Classifier: Programming Language :: Python :: Implementation :: CPython
Classifier: Programming Language :: Python :: Implementation :: PyPy
Classifier: Topic :: Software Development
Requires-Python: >=3.10
Requires-Dist: absence~=1.1
Requires-Dist: defusedxml
Requires-Dist: emcd-appcore~=1.0
Requires-Dist: frigid~=4.1
Requires-Dist: icecream-truck~=1.4
Requires-Dist: jinja2
Requires-Dist: packaging
Requires-Dist: typing-extensions
Requires-Dist: tyro
